vendor/__init__.py
vendor/__version__.py
vendor/admin.py
vendor/apps.py
vendor/config.py
vendor/fields.py
vendor/forms.py
vendor/integrations.py
vendor/settings.py
vendor/utils.py
vendor/api/__init__.py
vendor/api/urls.py
vendor/api/stripe/__init__.py
vendor/api/stripe/elements/__init__.py
vendor/api/stripe/elements/urls.py
vendor/api/stripe/elements/views.py
vendor/api/v1/__init__.py
vendor/api/v1/urls.py
vendor/api/v1/views.py
vendor/api/v1/authorizenet/__init__.py
vendor/api/v1/authorizenet/views.py
vendor/api/v1/stripe/__init__.py
vendor/api/v1/stripe/views.py
vendor/encrypt/__init__.py
vendor/encrypt/cleartext.py
vendor/migrations/0001_initial.py
vendor/migrations/0002_auto_20200912_0142.py
vendor/migrations/0003_auto_20200915_1839.py
vendor/migrations/0004_offer_offer_description.py
vendor/migrations/0005_auto_20200930_2037.py
vendor/migrations/0006_auto_20201005_2257.py
vendor/migrations/0007_offer_list_bundle_items.py
vendor/migrations/0008_offer_allow_multiple.py
vendor/migrations/0009_auto_20201111_0743.py
vendor/migrations/0010_auto_20201112_0138.py
vendor/migrations/0011_auto_20201120_1750.py
vendor/migrations/0012_auto_20201123_1848.py
vendor/migrations/0013_auto_20201202_1759.py
vendor/migrations/0014_term_types_update_value.py
vendor/migrations/0015_uuid_payments_receipts.py
vendor/migrations/0016_auto_20201203_2011.py
vendor/migrations/0017_auto_20201203_2107.py
vendor/migrations/0018_add_uuid_address_profile.py
vendor/migrations/0019_fill_uuid_address_profile.py
vendor/migrations/0020_lock_uuid_address_profile.py
vendor/migrations/0021_auto_20210408_2303.py
vendor/migrations/0022_offer_meta.py
vendor/migrations/0023_profile_null_false.py
vendor/migrations/0024_offer_deleted.py
vendor/migrations/0025_auto_20210914_0025.py
vendor/migrations/0026_auto_20210914_1209.py
vendor/migrations/0027_bugfix_vendor_notes_invoice_history.py
vendor/migrations/0028_add_trial_date_term_details.py
vendor/migrations/0029_alter_customerprofile_currency_and_more.py
django_vendor-0.7.1.dist-info/METADATA
django_vendor-0.7.1.dist-info/WHEEL
django_vendor-0.7.1.dist-info/top_level.txt
django_vendor-0.7.1.dist-info/RECORD
