Metadata-Version: 2.4
Name: django-vendor
Version: 0.7.1
Summary: Django App Toolkit for selling digital and physical goods online.
Author: Roberto Himmelbauer
Author-email: Grant Viklund <renderbox@gmail.com>
Project-URL: Homepage, https://github.com/renderbox/django-vendor
Project-URL: Bug Tracker, https://github.com/renderbox/django-vendor/issues
Project-URL: Documentation, https://github.com/renderbox/django-vendor
Keywords: django,app
Classifier: License :: OSI Approved :: MIT License
Classifier: Operating System :: OS Independent
Classifier: Intended Audience :: Developers
Classifier: Programming Language :: Python :: 3 :: Only
Classifier: Programming Language :: Python :: 3.10
Classifier: Programming Language :: Python :: 3.11
Classifier: Programming Language :: Python :: 3.12
Requires-Python: >=3.10
Requires-Dist: django<6.0,>=5.2
Requires-Dist: django-site-configs<0.5.0,>=0.4.0
Requires-Dist: django-integrations<0.5.0,>=0.4.0
Requires-Dist: iso4217<1.12.0
Provides-Extra: stripe
Requires-Dist: stripe; extra == "stripe"
Provides-Extra: authorizenet
Requires-Dist: authorizenet; extra == "authorizenet"
Provides-Extra: test
Requires-Dist: pytest; extra == "test"
Requires-Dist: pytest-django; extra == "test"
Requires-Dist: pytest-cov; extra == "test"
Requires-Dist: pytest-factoryboy; extra == "test"
Requires-Dist: pytest-mock; extra == "test"
Requires-Dist: pytest-asyncio; extra == "test"
Requires-Dist: pytest-bdd; extra == "test"
Requires-Dist: django-vendor[stripe]; extra == "test"
Provides-Extra: lint
Requires-Dist: black; extra == "lint"
Requires-Dist: flake8; extra == "lint"
Requires-Dist: flake8-black; extra == "lint"
Requires-Dist: isort; extra == "lint"
Requires-Dist: mypy; extra == "lint"
Requires-Dist: bandit; extra == "lint"
Provides-Extra: dev
Requires-Dist: django-vendor[test]; extra == "dev"
Requires-Dist: django-vendor[lint]; extra == "dev"
Requires-Dist: django-crispy-forms; extra == "dev"
Requires-Dist: django-site-configs; extra == "dev"
Requires-Dist: django-integrations; extra == "dev"
Requires-Dist: django-allauth; extra == "dev"
